src/mongodb_documentstore/__about__.py
src/mongodb_documentstore/__init__.py
src/mongodb_documentstore/documentstore.py
haystack_mongodb_documentstore-0.0.2.dist-info/METADATA
haystack_mongodb_documentstore-0.0.2.dist-info/WHEEL
haystack_mongodb_documentstore-0.0.2.dist-info/licenses/LICENSE.txt
haystack_mongodb_documentstore-0.0.2.dist-info/RECORD
