Metadata-Version: 2.1
Name: haystack-mongodb-documentstore
Version: 0.0.2
Project-URL: Documentation, https://github.com/unknown/mongodb-documentstore#readme
Project-URL: Issues, https://github.com/unknown/mongodb-documentstore/issues
Project-URL: Source, https://github.com/unknown/mongodb-documentstore
Author-email: deepset GmbH <info@deepset.ai>
Classifier: Development Status :: 4 - Beta
Classifier: Programming Language :: Python
Classifier: Programming Language :: Python :: 3.7
Classifier: Programming Language :: Python :: 3.8
Classifier: Programming Language :: Python :: 3.9
Classifier: Programming Language :: Python :: 3.10
Classifier: Programming Language :: Python :: 3.11
Classifier: Programming Language :: Python :: Implementation :: CPython
Classifier: Programming Language :: Python :: Implementation :: PyPy
Requires-Python: >=3.7
Requires-Dist: farm-haystack<2,>1
Requires-Dist: pymongo<5
